dblpcli/__init__.py
dblpcli/__main__.py
dblpcli/cli.py
dblpcli/api/__init__.py
dblpcli/api/client.py
dblpcli/formatters/__init__.py
dblpcli/formatters/json_formatter.py
dblpcli/formatters/table_formatter.py
dblpcli-0.1.0.dist-info/METADATA
dblpcli-0.1.0.dist-info/WHEEL
dblpcli-0.1.0.dist-info/entry_points.txt
dblpcli-0.1.0.dist-info/licenses/LICENSE
dblpcli-0.1.0.dist-info/RECORD
